[
    { 
        "nombre": "Café Americano", 
        "precio": 7000,
        "descripcion": "Café negro clásico, intenso y aromático"
    },
    { 
        "nombre": "Café Latte", 
        "precio": 7000,
        "descripcion": "Suave mezcla de café con leche cremosa"
    },
    { 
        "nombre": "Capuccino", 
        "precio": 8000,
        "descripcion": "Espuma perfecta con toque de canela"
    },
    { 
        "nombre": "Café Mocca", 
        "precio": 10000,
        "descripcion": "Café con chocolate, dulce y delicioso"
    },
    { "nombre": "Espresso", 
      "precio": 6000,
      "descripcion": "Café fuerte y concentrado"
    },
    { "nombre": "Café Frappé", 
      "precio": 10000,
      "descripcion": "Refrescante de consistencia espumosa y fría"
    },
    { "nombre": "Cafe Mocaccino", 
      "precio": 11000,
      "descripcion": "Café espresso + leche vaporizada y chocolate"
    },
    {"nombre": "Cafe Flat White", 
      "precio": 12000,
      "descripcion": "Café con sabor intenso a espresso y una textura cremosa"
    },
    { "nombre": "Cafe Prensado", 
      "precio": 10000,
      "descripcion": "Cafe con un sabor intenso y cuerpo completo, preparado con una prensa francesa"
    },
    { "nombre": "Chocolate Caliente", 
      "precio": 5000,
      "descripcion": "Chocolate caliente y delicioso"
    }
]